README.md
setup.py
IneryPy.egg-info/PKG-INFO
IneryPy.egg-info/SOURCES.txt
IneryPy.egg-info/dependency_links.txt
IneryPy.egg-info/requires.txt
IneryPy.egg-info/top_level.txt
api/__init__.py
api/cline.py
api/keys.py
api/types.py
api/utils.py