Metadata-Version: 1.0
Name: IneryPy
Version: 0.1
Summary: A package for RPC communication with Inery blockchain
Home-page: https://github.com/pnkg99/IneryPy.git
Author: Petar N
Author-email: pnkg99@example.com
License: MIT
Platform: UNKNOWN
